projeto/Relogio_Digital.v
/****************************************** (c) 2024 Wemerson Soares
  Módulo	: Clock_Digital
  Descrição : Módulo de relógio digital com contagem de horas, minutos e segundos.
              Suporta ajuste de tempo e exibição em 4 displays de 7 segmentos.
******************************************************************************/
// Módulo principal do relógio digital
module Relogio_Digital (
    input clk,               // Clock de 1Hz
    input reset,             // Sinal de reset
    input btn_ajuste,        // Botão para ajuste do relógio
    input btn_inc,           // Botão para incremento de horas ou minutos
    output [6:0] display_unidade_min,  // Unidades dos minutos a serem exibidas
    output [6:0] display_unidade_hora,  // Unidades das horas a serem exibidas
    output [6:0] display_dezena_hora,   // Dezenas das horas a serem exibidas
    output [6:0] display_dezena_min,    // Dezenas dos minutos a serem exibidas
    output [7:0] leds,        // LEDs para exibição da contagem de segundos
    output wire seg_ponto     // Ponto entre horas e minutos
);

    wire [5:0] segundos, minutos; // Sinais para armazenar os segundos e minutos
    wire [4:0] horas;             // Sinal para armazenar as horas
    wire ajustando;               // Sinal para indicar se o relógio está em modo de ajuste
    wire [1:0] estado;            // Estado atual do relógio (ajuste ou contagem normal)

    // Instâncias dos módulos utilizados
    Contador_Relogio contador (
        .clk(clk),                // Conexão do clock
        .reset(reset),            // Conexão do sinal de reset
        .btn_ajuste(btn_ajuste),  // Conexão do botão de ajuste
        .btn_inc(btn_inc),        // Conexão do botão de incremento
        .segundos(segundos),      // Sinal para os segundos
        .minutos(minutos),        // Sinal para os minutos
        .horas(horas),            // Sinal para as horas
        .ajustando(ajustando),    // Sinal de ajuste
        .estado(estado)           // Estado do ajuste
    );
    
    Display_7Seg display (
        .horas(horas),                        // Conexão das horas
        .minutos(minutos),                    // Conexão dos minutos
        .display_unidade_min(display_unidade_min),  // Conexão para a unidade dos minutos
        .display_unidade_hora(display_unidade_hora), // Conexão para a unidade das horas
        .display_dezena_hora(display_dezena_hora),   // Conexão para a dezena das horas
        .display_dezena_min(display_dezena_min)      // Conexão para a dezena dos minutos
    );
    
    assign seg_ponto = 1; // O ponto entre horas e minutos é sempre aceso
    assign leds = segundos; // Exibe o valor dos segundos nos LEDs
endmodule

// Módulo para contagem do relógio
module Contador_Relogio (
    input clk,                    // Clock de entrada
    input reset,                  // Sinal de reset
    input btn_ajuste,            // Botão de ajuste
    input btn_inc,               // Botão de incremento
    output reg [5:0] segundos = 0, // Registro para armazenar os segundos
    output reg [5:0] minutos = 0,   // Registro para armazenar os minutos
    output reg [4:0] horas = 0,     // Registro para armazenar as horas
    output reg ajustando = 0,       // Flag de ajuste
    output reg [1:0] estado = 0      // Estado do ajuste (0: rodando, 1: ajusta minutos, 2: ajusta horas)
);

    reg [3:0] dezena_min = 0; // Variável para armazenar as dezenas de minutos

    // Lógica de contagem do relógio
    always @(posedge clk or posedge reset) begin
        if (reset) begin
            // Inicializa os registros quando o sinal de reset é ativado
            horas <= 0;               // Reseta horas
            minutos <= 0;             // Reseta minutos
            dezena_min <= 0;          // Reseta dezenas de minutos
            segundos <= 0;            // Reseta segundos
            ajustando <= 0;           // Reseta flag de ajuste
            estado <= 0;              // Inicia no estado de contagem normal
        end else begin
            if (btn_ajuste) begin
                // Alterna entre os estados de ajuste e contagem
                estado <= (estado + 1) % 3; // Ciclo: 0 (rodando) -> 1 (ajustar minuto) -> 2 (ajustar hora) -> 0 (rodando)
            end
            
            if (estado == 0) begin
                // Estado de contagem normal
                segundos <= segundos + 1;  // Contagem de segundos
                if (segundos == 59) begin
                    segundos <= 0;              // Reseta segundos após 59
                    minutos <= minutos + 1;      // Incrementa minutos
                    if (minutos == 59) begin
                        minutos <= 0;              // Reseta minutos após 59
                        horas <= (horas + 1) % 24;  // Incrementa horas a cada 60 minutos
                    end
                end
            end else if (estado == 1) begin
                // Estado de ajuste de minutos
                if (btn_inc) begin
                    // Incrementa minutos ao pressionar o botão de incremento
                    if (minutos % 10 == 9) begin
                        dezena_min <= (dezena_min + 1) % 6; // Incrementa as dezenas se unidades chegarem a 9
                    end
                    minutos <= (minutos + 1) % 60;  // Incrementa minutos e reseta após 59
                end
            end else if (estado == 2) begin
                // Estado de ajuste de horas
                if (btn_inc) begin
                    // Incrementa horas ao pressionar o botão de incremento
                    horas <= (horas + 1) % 24;  // Incrementa horas e reseta após 23
                end
            end
        end
    end
endmodule

// Módulo para exibição nos displays de 7 segmentos
module Display_7Seg (
    input [4:0] horas,          // Horas a serem exibidas
    input [5:0] minutos,        // Minutos a serem exibidos
    output reg [6:0] display_unidade_min,  // Unidades dos minutos a serem exibidas
    output reg [6:0] display_unidade_hora, // Unidades das horas a serem exibidas
    output reg [6:0] display_dezena_hora,  // Dezenas das horas a serem exibidas
    output reg [6:0] display_dezena_min    // Dezenas dos minutos a serem exibidas
);

    // Sempre que houver mudança nas horas ou minutos, atualiza os displays
    always @(*) begin
        display_dezena_hora = hora_para_7seg(horas / 10);        // Converte as dezenas das horas para 7 segmentos
        display_unidade_hora = hora_para_7seg(horas % 10);       // Converte as unidades das horas para 7 segmentos
        display_dezena_min = min_para_7seg(minutos / 10);        // Converte as dezenas dos minutos para 7 segmentos
        display_unidade_min = min_para_7seg(minutos % 10);       // Converte as unidades dos minutos para 7 segmentos
    end

    // Função para converter horas em formato para displays de 7 segmentos
    function [6:0] hora_para_7seg(input [3:0] valor);
        case (valor)
            0: hora_para_7seg = 7'b1111110; // 0 - acende a, b, c, d, e, f
            1: hora_para_7seg = 7'b0110000; // 1 - acende b, c
            2: hora_para_7seg = 7'b1101101; // 2 - acende a, b, d, e, g
            3: hora_para_7seg = 7'b1111001; // 3 - acende a, b, c, d, g
            4: hora_para_7seg = 7'b0110011; // 4 - acende b, c, f, g
            5: hora_para_7seg = 7'b1011011; // 5 - acende a, c, d, f, g
            6: hora_para_7seg = 7'b1011111; // 6 - acende a, c, d, e, f, g
            7: hora_para_7seg = 7'b1110000; // 7 - acende a, b, c
            8: hora_para_7seg = 7'b1111111; // 8 - acende todos
            9: hora_para_7seg = 7'b1110011; // 9 - acende a, b, c, d, f, g
            default: hora_para_7seg = 7'b0000000; // Desligado
        endcase
    endfunction

    // Função para converter minutos em formato para displays de 7 segmentos
    function [6:0] min_para_7seg(input [3:0] valor);
        case (valor)
            0: min_para_7seg = 7'b1111110; // 0 - acende a, b, c, d, e, f
            1: min_para_7seg = 7'b0110000; // 1 - acende b, c
            2: min_para_7seg = 7'b1101101; // 2 - acende a, b, d, e, g
            3: min_para_7seg = 7'b1111001; // 3 - acende a, b, c, d, g
            4: min_para_7seg = 7'b0110011; // 4 - acende b, c, f, g
            5: min_para_7seg = 7'b1011011; // 5 - acende a, c, d, f, g
            6: min_para_7seg = 7'b1011111; // 6 - acende a, c, d, e, f, g
            7: min_para_7seg = 7'b1110000; // 7 - acende a, b, c
            8: min_para_7seg = 7'b1111111; // 8 - acende todos
            9: min_para_7seg = 7'b1110011; // 9 - acende a, b, c, d, f, g
            default: min_para_7seg = 7'b0000000; // Desligado
        endcase
    endfunction
endmodule

simulação/tb_Relogio_Digital.v
module tb_Relogio_Digital;

  // Declaração dos sinais de entrada e saída
  reg clk;
  reg reset;
  reg btn_ajuste;
  reg btn_inc;
  wire [6:0] display_unidade_min;
  wire [6:0] display_unidade_hora;
  wire [6:0] display_dezena_hora;
  wire [6:0] display_dezena_min;
  wire [7:0] leds;
  wire seg_ponto;

  // Instanciando o módulo Relogio_Digital
  Relogio_Digital uut (
    .clk(clk),
    .reset(reset),
    .btn_ajuste(btn_ajuste),
    .btn_inc(btn_inc),
    .display_unidade_min(display_unidade_min),
    .display_unidade_hora(display_unidade_hora),
    .display_dezena_hora(display_dezena_hora),
    .display_dezena_min(display_dezena_min),
    .leds(leds),
    .seg_ponto(seg_ponto)
  );

  // Geração do clock (1 Hz)
  initial begin
    clk = 0;
    forever #500 clk = ~clk;  // Alterna o clock a cada 500 unidades de tempo (simulando 1 Hz)
  end

  // Gerando o arquivo VCD para visualizar no GTKWave
  initial begin
    $dumpfile("dump.vcd");  // Nome do arquivo de dump de ondas
    $dumpvars(0, tb_Relogio_Digital);  // Dump de todas as variáveis do testbench
  end

  // Simulação
  initial begin
    // Inicializa os sinais
    reset = 1;
    btn_ajuste = 0;
    btn_inc = 0;

    // Aguardar alguns ciclos de clock
    #1000;
    
    // Libera o reset e começa a simulação
    reset = 0;
    
    // Simulação da contagem normal de tempo
    #5000;
    
    // Ajusta o relógio (estado de ajuste de minutos)
    btn_ajuste = 1;
    #1000;
    btn_ajuste = 0;

    // Incrementa minutos
    btn_inc = 1;
    #1000;
    btn_inc = 0;

    // Aguardar alguns ciclos para observar o incremento de minutos
    #5000;

    // Ajusta o relógio (estado de ajuste de horas)
    btn_ajuste = 1;
    #1000;
    btn_ajuste = 0;

    // Incrementa horas
    btn_inc = 1;
    #1000;
    btn_inc = 0;

    // Aguardar mais alguns ciclos para observar o incremento de horas
    #5000;

    // Finalizar a simulação
    $finish;
  end

endmodule

simulação/dump.vcd
$date
	Sun Sep 22 13:23:32 2024
$end
$version
	Icarus Verilog
$end
$timescale
	1s
$end
$scope module tb_Relogio_Digital $end
$var wire 1 ! seg_ponto $end
$var wire 8 " leds [7:0] $end
$var wire 7 # display_unidade_min [6:0] $end
$var wire 7 $ display_unidade_hora [6:0] $end
$var wire 7 % display_dezena_min [6:0] $end
$var wire 7 & display_dezena_hora [6:0] $end
$var reg 1 ' btn_ajuste $end
$var reg 1 ( btn_inc $end
$var reg 1 ) clk $end
$var reg 1 * reset $end
$scope module uut $end
$var wire 1 ' btn_ajuste $end
$var wire 1 ( btn_inc $end
$var wire 1 ) clk $end
$var wire 1 * reset $end
$var wire 1 ! seg_ponto $end
$var wire 6 + segundos [5:0] $end
$var wire 6 , minutos [5:0] $end
$var wire 8 - leds [7:0] $end
$var wire 5 . horas [4:0] $end
$var wire 2 / estado [1:0] $end
$var wire 7 0 display_unidade_min [6:0] $end
$var wire 7 1 display_unidade_hora [6:0] $end
$var wire 7 2 display_dezena_min [6:0] $end
$var wire 7 3 display_dezena_hora [6:0] $end
$var wire 1 4 ajustando $end
$scope module contador $end
$var wire 1 ' btn_ajuste $end
$var wire 1 ( btn_inc $end
$var wire 1 ) clk $end
$var wire 1 * reset $end
$var reg 1 4 ajustando $end
$var reg 4 5 dezena_min [3:0] $end
$var reg 2 6 estado [1:0] $end
$var reg 5 7 horas [4:0] $end
$var reg 6 8 minutos [5:0] $end
$var reg 6 9 segundos [5:0] $end
$upscope $end
$scope module display $end
$var wire 5 : horas [4:0] $end
$var wire 6 ; minutos [5:0] $end
$var reg 7 < display_dezena_hora [6:0] $end
$var reg 7 = display_dezena_min [6:0] $end
$var reg 7 > display_unidade_hora [6:0] $end
$var reg 7 ? display_unidade_min [6:0] $end
$scope function hora_para_7seg $end
$var reg 4 @ valor [3:0] $end
$upscope $end
$scope function min_para_7seg $end
$var reg 4 A valor [3:0] $end
$upscope $end
$upscope $end
$upscope $end
$upscope $end
$enddefinitions $end
$comment Show the parameter values. $end
$dumpall
$end
#0
$dumpvars
b0 A
b0 @
b111111 ?
b111111 >
b111111 =
b111111 <
b0 ;
b0 :
b0 9
b0 8
b0 7
b0 6
b0 5
04
b111111 3
b111111 2
b111111 1
b111111 0
b0 /
b0 .
b0 -
b0 ,
b0 +
1*
0)
0(
0'
b111111 &
b111111 %
b111111 $
b111111 #
b0 "
1!
$end
#500
1)
#1000
0)
0*
#1500
b1 "
b1 -
b1 +
b1 9
1)
#2000
0)
#2500
b10 "
b10 -
b10 +
b10 9
1)
#3000
0)
#3500
b11 "
b11 -
b11 +
b11 9
1)
#4000
0)
#4500
b100 "
b100 -
b100 +
b100 9
1)
#5000
0)
#5500
b101 "
b101 -
b101 +
b101 9
1)
#6000
0)
1'
#6500
b110 "
b110 -
b110 +
b110 9
b1 /
b1 6
1)
#7000
0)
1(
0'
#7500
b110 #
b110 0
b110 ?
b1 A
b1 ,
b1 8
b1 ;
1)
#8000
0)
0(
#8500
1)
#9000
0)
#9500
1)
#10000
0)
#10500
1)
#11000
0)
#11500
1)
#12000
0)
#12500
1)
#13000
0)
1'
#13500
b10 /
b10 6
1)
#14000
0)
1(
0'
#14500
b1 A
b110 $
b110 1
b110 >
b1 @
b1 .
b1 7
b1 :
1)
#15000
0)
0(
